hjoin/__init__.py
hjoin/core.py
hjoin-0.2.0.dist-info/AUTHORS.rst
hjoin-0.2.0.dist-info/LICENSE
hjoin-0.2.0.dist-info/METADATA
hjoin-0.2.0.dist-info/WHEEL
hjoin-0.2.0.dist-info/top_level.txt
hjoin-0.2.0.dist-info/RECORD
